abacusagent/__init__.py
abacusagent/constant.py
abacusagent/create_template.py
abacusagent/env.py
abacusagent/google-adk-agent-template.py
abacusagent/init_mcp.py
abacusagent/main.py
abacusagent/prompt.py
abacusagent/version.py
abacusagent/modules/__init__.py
abacusagent/modules/abacus.py
abacusagent/modules/bader.py
abacusagent/modules/band.py
abacusagent/modules/cube.py
abacusagent/modules/dos.py
abacusagent/modules/elastic.py
abacusagent/modules/eos.py
abacusagent/modules/md.py
abacusagent/modules/phonon.py
abacusagent/modules/pyatb.py
abacusagent/modules/relax.py
abacusagent/modules/scf.py
abacusagent/modules/structure_editor.py
abacusagent/modules/structure_generator.py
abacusagent/modules/symmetry.py
abacusagent/modules/tool_wrapper.py
abacusagent/modules/vacancy.py
abacusagent/modules/vibration.py
abacusagent/modules/work_function.py
abacusagent/modules/submodules/abacus.py
abacusagent/modules/submodules/bader.py
abacusagent/modules/submodules/band.py
abacusagent/modules/submodules/cube.py
abacusagent/modules/submodules/deeptb_tool.py
abacusagent/modules/submodules/dos.py
abacusagent/modules/submodules/elastic.py
abacusagent/modules/submodules/eos.py
abacusagent/modules/submodules/jdos_pyatb.py
abacusagent/modules/submodules/md.py
abacusagent/modules/submodules/phonon.py
abacusagent/modules/submodules/pyatb.py
abacusagent/modules/submodules/relax.py
abacusagent/modules/submodules/scf.py
abacusagent/modules/submodules/structure_editor.py
abacusagent/modules/submodules/structure_generator.py
abacusagent/modules/submodules/vacancy.py
abacusagent/modules/submodules/vibration.py
abacusagent/modules/submodules/work_function.py
abacusagent/modules/util/__init__.py
abacusagent/modules/util/chemical_elements.py
abacusagent/modules/util/comm.py
abacusagent/modules/util/control.py
abacusagent/modules/util/cube_manipulator.py
abacusagent/modules/util/pyatb.py
abacusagent/modules/util/symmetry.py
abacusagent-0.2.5.dist-info/licenses/LICENSE
abacusagent-0.2.5.dist-info/METADATA
abacusagent-0.2.5.dist-info/WHEEL
abacusagent-0.2.5.dist-info/entry_points.txt
abacusagent-0.2.5.dist-info/top_level.txt
abacusagent-0.2.5.dist-info/RECORD
