Metadata-Version: 2.4
Name: abacusagent
Version: 0.2.5
Summary: ABACUS agent tools for connecting LLMs to first-principles calculation workflows
License:                    GNU LESSER GENERAL PUBLIC LICENSE
Classifier: Development Status :: 3 - Alpha
Classifier: Intended Audience :: Science/Research
Classifier: Operating System :: OS Independent
Classifier: Programming Language :: Python :: 3
Classifier: Topic :: Scientific/Engineering :: Physics
Classifier: Topic :: Scientific/Engineering :: Chemistry
Classifier: Topic :: Scientific/Engineering :: Artificial Intelligence
Requires-Python: >=3.11
License-File: LICENSE
Requires-Dist: abacustest>=0.4.51
Requires-Dist: numpy<2.0
Requires-Dist: pymatgen>=2025.5.28
Requires-Dist: bohr-agent-sdk==0.1.121
Requires-Dist: bohrium-sdk==0.13.0
Requires-Dist: dpdata>=0.2.24
Requires-Dist: regex==2024.11.6
Requires-Dist: pyatb==1.1.1
Provides-Extra: dev
Requires-Dist: mcp>=1.10.0; extra == "dev"
Requires-Dist: science-agent-sdk; extra == "dev"
Dynamic: license-file
